radio_dreams/__init__.py
radio_dreams/interferometer.py
radio_dreams-0.3.5.dist-info/LICENSE
radio_dreams-0.3.5.dist-info/WHEEL
radio_dreams-0.3.5.dist-info/METADATA
radio_dreams-0.3.5.dist-info/RECORD
