Metadata-Version: 2.1
Name: radio-dreams
Version: 0.3.5
Summary: Imagined Interferometers
Home-page: https://github.com/amanchokshi/radio-dreams
License: MIT
Keywords: radio,interferometer,simulator
Author: Aman Chokshi
Author-email: achokshi@student.unimelb.edu.au
Requires-Python: >=3.7,<3.10
Classifier: License :: OSI Approved :: MIT License
Classifier: Programming Language :: Python :: 3
Classifier: Programming Language :: Python :: 3.7
Classifier: Programming Language :: Python :: 3.8
Requires-Dist: numba (>=0.53.1,<0.54.0)
Requires-Dist: numpy (>=1.20.3,<2.0.0)
Requires-Dist: scipy (>=1.6.3,<2.0.0)
Requires-Dist: skyfield (>=1.39,<2.0)
Project-URL: Documentation, https://radio-dreams.readthedocs.io
Project-URL: Repository, https://github.com/amanchokshi/radio-dreams
